marvelous/__init__.py
marvelous/character.py
marvelous/characters_list.py
marvelous/comic.py
marvelous/comics_list.py
marvelous/creator.py
marvelous/creators_list.py
marvelous/dates.py
marvelous/events.py
marvelous/exceptions.py
marvelous/prices.py
marvelous/series.py
marvelous/series_list.py
marvelous/session.py
marvelous/sqlite_cache.py
marvelous/urls.py
marvelous-1.4.5.dist-info/LICENSE
marvelous-1.4.5.dist-info/METADATA
marvelous-1.4.5.dist-info/WHEEL
marvelous-1.4.5.dist-info/RECORD
