Metadata-Version: 2.1
Name: marvelous
Version: 1.4.5
Summary: Marvel API wrapper for python.
License: MIT
Author: Robert Kuykendall
Author-email: robert@rkuykendall.com
Maintainer: Robert Kuykendall
Maintainer-email: robert@rkuykendall.com
Requires-Python: >=3.7,<4.0
Classifier: Intended Audience :: Developers
Classifier: License :: OSI Approved :: MIT License
Classifier: Natural Language :: English
Classifier: Operating System :: OS Independent
Classifier: Programming Language :: Python
Classifier: Programming Language :: Python :: 3
Classifier: Programming Language :: Python :: 3.7
Classifier: Programming Language :: Python :: 3.8
Classifier: Programming Language :: Python :: 3.9
Classifier: Programming Language :: Python :: 3.10
Classifier: Programming Language :: Python :: 3.11
Classifier: Programming Language :: Python :: 3.12
Classifier: Topic :: Utilities
Provides-Extra: docs
Requires-Dist: marshmallow (>=3.13.0,<4.0.0)
Requires-Dist: requests (>=2.26.0,<3.0.0)
Requires-Dist: sphinx-rtd-theme (>=0.5.2,<0.6.0) ; extra == "docs"
Project-URL: Bug Tracker, https://github.com/rkuykendall/marvelous/issues
Project-URL: Homepage, https://github.com/rkuykendall/marvelous
